example_package/__init__.py
example_package/hello.py
helloworldyaroslav2131234-0.2.0.dist-info/METADATA
helloworldyaroslav2131234-0.2.0.dist-info/WHEEL
helloworldyaroslav2131234-0.2.0.dist-info/top_level.txt
helloworldyaroslav2131234-0.2.0.dist-info/RECORD
